src/__init__.py
src/configuration.py
src/funciones.py
src/main_analisis.py
src/main_fichero.py
src/main_interactivo.py
src/main_visualizacion.py
src/algoritmos/__init__.py
src/algoritmos/algoritmogenetico.py
src/algoritmos/algoritmomemetico.py
src/algoritmos/enfriamientosimulado.py
src/algoritmos/grasp.py
src/algoritmos/greedy.py
src/datos/__init__.py
src/datos/lectura_datos.py
src/datos/visualizacion.py
GranadaCultura-0.1.2.dist-info/METADATA
GranadaCultura-0.1.2.dist-info/WHEEL
GranadaCultura-0.1.2.dist-info/top_level.txt
GranadaCultura-0.1.2.dist-info/RECORD
