Metadata-Version: 2.1
Name: GranadaCultura
Version: 0.1.2
Summary: Descripción del paquete GranadaCultura
Home-page: https://github.com/lusangom/GranadaCultura
Author: Lucia Sanchez Montes Gomez
Author-email: lsangom@correo.ugr.es
License: UNKNOWN
Platform: UNKNOWN
Classifier: Programming Language :: Python :: 3
Classifier: Operating System :: OS Independent
Requires-Python: >=3.6
Requires-Dist: folium (==0.15.1)
Requires-Dist: geopandas (==0.14.3)
Requires-Dist: matplotlib (==3.8.2)
Requires-Dist: numpy (==1.23.5)
Requires-Dist: osmnx (==1.9.1)
Requires-Dist: pandas (==1.5.2)
